ebay.ini
setup.py
dist/easyBay-0.1dev-py2.4.egg
easyBay/__init__.py
easyBay/ebay.ini
easyBay.egg-info/PKG-INFO
easyBay.egg-info/SOURCES.txt
easyBay.egg-info/top_level.txt
