Metadata-Version: 1.0
Name: easyBay
Version: 0.1dev
Summary: A simple way to talk to eBay (manage listings, gather data) with Python.
Home-page: http://exogen.case.edu/easyBay/
Author: Brian Beck
Author-email: exogen@gmail.com
License: PSF
Keywords: ebay
Platform: UNKNOWN
